qhal/__about__.py
qhal/__init__.py
qhal/hal/__init__.py
qhal/hal/_circuit.py
qhal/hal/_commands.py
qhal/hal/_hardware_abstraction_layer.py
qhal/hal/_measurements.py
qhal/hal/_qasm.py
qhal/hal/_responses.py
qhal/hal/_utils.py
qhal/quantum_simulators/__init__.py
qhal/quantum_simulators/_interface_quantum_simulator.py
qhal/quantum_simulators/_projectq_quantum_simulator.py
qhal-0.3.2.data/scripts/qasm_to_qhal.py
qhal-0.3.2.dist-info/LICENSE
qhal-0.3.2.dist-info/METADATA
qhal-0.3.2.dist-info/WHEEL
qhal-0.3.2.dist-info/top_level.txt
qhal-0.3.2.dist-info/RECORD
