Metadata-Version: 2.1
Name: qhal
Version: 0.3.2
Summary: Quantum HAL
Home-page: https://gitlab.npl.co.uk/quantum-hardware-abstraction-layer/qhal
Author: ISCF Steering committee
Author-email: 
License: Apache 2.0
Platform: 
Classifier: Development Status :: 4 - Beta
Classifier: Environment :: Console
Classifier: Intended Audience :: Developers
Classifier: Intended Audience :: Science/Research
Classifier: License :: Free for non-commercial use
Classifier: Operating System :: POSIX :: Linux
Classifier: Programming Language :: Python :: 3
Requires-Python: >=3.8
License-File: LICENSE
Requires-Dist: numpy
Requires-Dist: projectq
Requires-Dist: qiskit
